ansible_creator/__init__.py
ansible_creator/__main__.py
ansible_creator/_version.py
ansible_creator/_version.pyi
ansible_creator/arg_parser.py
ansible_creator/cli.py
ansible_creator/compat.py
ansible_creator/config.py
ansible_creator/constants.py
ansible_creator/exceptions.py
ansible_creator/output.py
ansible_creator/py.typed
ansible_creator/templar.py
ansible_creator/types.py
ansible_creator/utils.py
ansible_creator/resources/collection_project/.isort.cfg.j2
ansible_creator/resources/collection_project/.pre-commit-config.yaml.j2
ansible_creator/resources/collection_project/.prettierignore.j2
ansible_creator/resources/collection_project/CHANGELOG.rst
ansible_creator/resources/collection_project/CODE_OF_CONDUCT.md
ansible_creator/resources/collection_project/CONTRIBUTING
ansible_creator/resources/collection_project/LICENSE.j2
ansible_creator/resources/collection_project/MAINTAINERS
ansible_creator/resources/collection_project/README.md.j2
ansible_creator/resources/collection_project/galaxy.yml.j2
ansible_creator/resources/collection_project/pyproject.toml.j2
ansible_creator/resources/collection_project/requirements.txt
ansible_creator/resources/collection_project/test-requirements.txt
ansible_creator/resources/collection_project/tox-ansible.ini.j2
ansible_creator/resources/collection_project/.github/workflows/release.yml.j2
ansible_creator/resources/collection_project/.github/workflows/tests.yml.j2
ansible_creator/resources/collection_project/changelogs/config.yaml.j2
ansible_creator/resources/collection_project/docs/.keep
ansible_creator/resources/collection_project/docs/docsite/links.yml.j2
ansible_creator/resources/collection_project/extensions/eda/rulebooks/rulebook.yml.j2
ansible_creator/resources/collection_project/extensions/molecule/integration_hello_world/molecule.yml.j2
ansible_creator/resources/collection_project/extensions/molecule/utils/playbooks/converge.yml.j2
ansible_creator/resources/collection_project/extensions/molecule/utils/playbooks/noop.yml.j2
ansible_creator-25.11.0.dist-info/licenses/LICENSE
ansible_creator-25.11.0.dist-info/METADATA
ansible_creator-25.11.0.dist-info/WHEEL
ansible_creator-25.11.0.dist-info/entry_points.txt
ansible_creator-25.11.0.dist-info/top_level.txt
ansible_creator-25.11.0.dist-info/RECORD
