Metadata-Version: 2.4
Name: ansible-creator
Version: 25.11.0
Summary: A CLI tool for scaffolding Ansible Content.
Author-email: Nilashish Chakarborty <nchakrab@redhat.com>
Maintainer-email: Ansible by Red Hat <info@ansible.com>
License: Apache
Project-URL: changelog, https://github.com/ansible/ansible-creator/releases
Project-URL: documentation, https://ansible.readthedocs.io/projects/creator/
Project-URL: homepage, https://github.com/ansible/ansible-creator
Project-URL: repository, https://github.com/ansible/ansible-creator
Keywords: ansible
Classifier: Development Status :: 5 - Production/Stable
Classifier: Intended Audience :: Developers
Classifier: License :: OSI Approved :: Apache Software License
Classifier: Operating System :: OS Independent
Classifier: Programming Language :: Python
Classifier: Programming Language :: Python :: 3
Classifier: Programming Language :: Python :: 3 :: Only
Classifier: Programming Language :: Python :: 3.10
Classifier: Programming Language :: Python :: 3.11
Classifier: Programming Language :: Python :: 3.12
Classifier: Programming Language :: Python :: 3.13
Classifier: Programming Language :: Python :: Implementation :: CPython
Classifier: Topic :: Software Development :: Code Generators
Classifier: Topic :: Utilities
Requires-Python: >=3.10
License-File: LICENSE
Requires-Dist: importlib-resources; python_full_version < "3.10"
Requires-Dist: jinja2>=3.1.2
Requires-Dist: pyyaml>=6.0.2
Dynamic: license-file
